fate_crypto-0.3.0.dist-info/METADATA
fate_crypto-0.3.0.dist-info/WHEEL
fate_crypto.libs/libgcc_s-2ad2d535.so.1
fate_crypto/psi/__init__.pyi
fate_crypto/psi/__init__.py
fate_crypto/hash/__init__.pyi
fate_crypto/hash/__init__.py
fate_crypto/__init__.py
fate_crypto/fate_crypto.cpython-39-x86_64-linux-gnu.so
fate_crypto-0.3.0.dist-info/RECORD
