Metadata-Version: 2.1
Name: fate_crypto
Version: 0.3.0
Classifier: Programming Language :: Rust
Classifier: Programming Language :: Python :: Implementation :: CPython
Summary: crypto implemented or wrapped using rust
Requires-Python: >=3.6
